better_image.py
setup.cfg
setup.py
BetterImageExtension.egg-info/PKG-INFO
BetterImageExtension.egg-info/SOURCES.txt
BetterImageExtension.egg-info/dependency_links.txt
BetterImageExtension.egg-info/requires.txt
BetterImageExtension.egg-info/top_level.txt