Metadata-Version: 1.1
Name: BetterImageExtension
Version: 0.0.1
Summary: Python-Markdown extension to add additional image syntax eg print and web sizes from a single image
Home-page: http://neurobashing.com/
Author: Gregg Thomason
Author-email: gregg@neurobashing.com
License: UNKNOWN
Platform: UNKNOWN
Classifier: Development Status :: 4 - Beta
Classifier: Operating System :: OS Independent
Classifier: License :: OSI Approved :: BSD License
Classifier: Intended Audience :: Developers
Classifier: Environment :: Web Environment
Classifier: Programming Language :: Python
Classifier: Topic :: Text Processing :: Filters
Classifier: Topic :: Text Processing :: Markup :: HTML
